LICENSE
MANIFEST.in
README.rst
ez_setup.py
setup.py
multi_registry/__init__.py
multi_registry.egg-info/PKG-INFO
multi_registry.egg-info/SOURCES.txt
multi_registry.egg-info/dependency_links.txt
multi_registry.egg-info/requires.txt
multi_registry.egg-info/top_level.txt
multi_registry/tests/README
multi_registry/tests/__init__.py
multi_registry/tests/runtests.py
multi_registry/tests/settings1.py
multi_registry/tests/settings2.py