Metadata-Version: 1.0
Name: multi-registry
Version: 0.0.2
Summary: A module that aggregates key-value attributes from multiple sources
Home-page: http://askbot.org
Author: Evgeny.Fadeev
Author-email: evgeny.fadeev@gmail.com
License: BSD
Keywords: settings,registry
Platform: UNKNOWN
Classifier: Development Status :: 4 - Beta
Classifier: Intended Audience :: Developers
Classifier: License :: OSI Approved :: BSD License
Classifier: Operating System :: OS Independent
Classifier: Programming Language :: Python :: 2.5
Classifier: Programming Language :: Python :: 2.6
Classifier: Programming Language :: Python :: 2.7
Classifier: Topic :: Communications :: Usenet News
